onequant/__init__.py
onequant/api/__init__.py
onequant/api/quotes.py
onequant/api/request.py
onequant/api/strategies.py
onequant/api/trades.py
onequant/api/wrapper.py
onequant/data_wash/__init__.py
onequant/data_wash/preprocess_returns.py
onequant/indicators/KDJ.py
onequant/indicators/SAR.py
onequant/indicators/__init__.py
onequant/onequant.py
onequant/portfolio/__init__.py
onequant/portfolio/polts.py
onequant/portfolio/strategy_folio.py
onequant/util/__init__.py
onequant/util/datetime.py
onequant-0.1.2.dist-info/LICENSE
onequant-0.1.2.dist-info/METADATA
onequant-0.1.2.dist-info/WHEEL
onequant-0.1.2.dist-info/RECORD
